wildhost.py
wildhost-0.0.4.dist-info/LICENSE
wildhost-0.0.4.dist-info/WHEEL
wildhost-0.0.4.dist-info/METADATA
wildhost-0.0.4.dist-info/RECORD
