Metadata-Version: 2.1
Name: wildhost
Version: 0.0.4
Summary: Checks wildcard domain names
Home-page: https://github.com/havefish/wildhost
License: UNKNOWN
Author: havefish
Author-email: havefish@protonmail.com
Classifier: Intended Audience :: Developers
Classifier: License :: OSI Approved :: MIT License
Classifier: Programming Language :: Python :: 3.6
Classifier: Programming Language :: Python :: 3.7
Classifier: Programming Language :: Python :: 3.8
Classifier: Topic :: Software Development :: Libraries :: Python Modules
Requires-Dist: tldextract
